earwax_server/__init__.py
earwax_server-0.1.2.dist-info/AUTHORS
earwax_server-0.1.2.dist-info/LICENSE
earwax_server-0.1.2.dist-info/METADATA
earwax_server-0.1.2.dist-info/WHEEL
earwax_server-0.1.2.dist-info/entry_points.txt
earwax_server-0.1.2.dist-info/pbr.json
earwax_server-0.1.2.dist-info/top_level.txt
earwax_server-0.1.2.dist-info/RECORD
