Metadata-Version: 2.1
Name: earwax-server
Version: 0.1.2
Summary: A Python module for making event-driven line servers for use with Earwax
Home-page: http://earwax.readthedocs.io/
Author: Chris Norman
Author-email: chris.norman2@googlemail.com
License: MPL
Platform: UNKNOWN
Requires-Dist: attrs
Requires-Dist: gevent
